escaper_lite/__init__.py
escaper_lite/xutils.cp310-win_amd64.pyd
escaper_lite/xutils.cp36-win_amd64.pyd
escaper_lite/xutils.cp37-win_amd64.pyd
escaper_lite/xutils.cp38-win_amd64.pyd
escaper_lite/xutils.cp39-win_amd64.pyd
escaper_lite/xutils.cpython-310-x86_64-linux-gnu.so
escaper_lite/xutils.cpython-36m-x86_64-linux-gnu.so
escaper_lite/xutils.cpython-37m-x86_64-linux-gnu.so
escaper_lite/xutils.cpython-38-x86_64-linux-gnu.so
escaper_lite/xutils.cpython-39-x86_64-linux-gnu.so
escaper_lite-0.1.1.dist-info/METADATA
escaper_lite-0.1.1.dist-info/WHEEL
escaper_lite-0.1.1.dist-info/top_level.txt
escaper_lite-0.1.1.dist-info/RECORD
